lockpy/__init__.py
lockpy/private.py
lockpy/singleton.py
lockpy-1.0.0.dist-info/licenses/LICENSE
lockpy-1.0.0.dist-info/METADATA
lockpy-1.0.0.dist-info/WHEEL
lockpy-1.0.0.dist-info/top_level.txt
lockpy-1.0.0.dist-info/RECORD
