Metadata-Version: 2.4
Name: lockpy
Version: 1.0.0
Summary: Static typed-style access modifiers and patterns for Python
Author-email: Vibhinn Singhal <vibhinnsinghal@gmail.com>
License: MIT License
Project-URL: Homepage, https://github.com/VibhinnS/lockpy
Project-URL: Bug Tracker, https://github.com/VibhinnS/lockpy/issues
Keywords: python,decorators,access control,singleton,private
Classifier: Programming Language :: Python :: 3
Classifier: License :: OSI Approved :: MIT License
Classifier: Operating System :: OS Independent
Requires-Python: >=3.8
License-File: LICENSE
Dynamic: license-file
